treams/__init__.py
treams/_core.py
treams/_lattice.py
treams/_material.py
treams/_operators.py
treams/_smatrix.py
treams/_tmatrix.py
treams/coeffs.cp38-win_amd64.pyd
treams/config.cp38-win_amd64.pyd
treams/cw.cp38-win_amd64.pyd
treams/ebcm.py
treams/io.py
treams/misc.py
treams/pw.cp38-win_amd64.pyd
treams/sw.cp38-win_amd64.pyd
treams/util.py
treams/lattice/__init__.py
treams/lattice/_dsum.cp38-win_amd64.pyd
treams/lattice/_esum.cp38-win_amd64.pyd
treams/lattice/_gufuncs.cp38-win_amd64.pyd
treams/lattice/_misc.cp38-win_amd64.pyd
treams/lattice/cython_lattice.cp38-win_amd64.pyd
treams/special/__init__.py
treams/special/_bessel.cp38-win_amd64.pyd
treams/special/_coord.cp38-win_amd64.pyd
treams/special/_gufuncs.cp38-win_amd64.pyd
treams/special/_integrals.cp38-win_amd64.pyd
treams/special/_misc.cp38-win_amd64.pyd
treams/special/_ufuncs.cp38-win_amd64.pyd
treams/special/_waves.cp38-win_amd64.pyd
treams/special/_wigner3j.cp38-win_amd64.pyd
treams/special/_wignerd.cp38-win_amd64.pyd
treams/special/cython_special.cp38-win_amd64.pyd
treams-0.4.5.dist-info/LICENSE
treams-0.4.5.dist-info/METADATA
treams-0.4.5.dist-info/WHEEL
treams-0.4.5.dist-info/top_level.txt
treams-0.4.5.dist-info/RECORD
